atl_observe/__init__.py
atl_observe/decorator.py
atl_observe/lib/__init__.py
atl_observe/lib/logger.py
atl_observe/lib/metrics.py
atl_observe/lib/slack.py
atl_observe/lib/utils.py
atl_observe-1.1.0.dist-info/LICENCE
atl_observe-1.1.0.dist-info/METADATA
atl_observe-1.1.0.dist-info/WHEEL
atl_observe-1.1.0.dist-info/top_level.txt
atl_observe-1.1.0.dist-info/RECORD
