Metadata-Version: 2.1
Name: atl-observe
Version: 1.1.0
Summary: A decorator to unify logging, metrics and notifications.
Home-page: https://github.com/atlassian-labs/observe
Author: Georg Kasper
License: UNKNOWN
Platform: UNKNOWN
Requires-Dist: requests
Requires-Dist: datadog
